jpndlpy/__init__.py
jpndlpy/client.py
jpndlpy/client_base.py
jpndlpy/exceptions.py
jpndlpy/item_entity.py
jpndlpy/request.py
jpndlpy/response.py
jpndlpy/validator.py
jpndlpy-0.2.0.dist-info/METADATA
jpndlpy-0.2.0.dist-info/RECORD
jpndlpy-0.2.0.dist-info/WHEEL
jpndlpy-0.2.0.dist-info/top_level.txt
tests/__init__.py
tests/test_client.py
tests/test_main.py
tests/test_validator.py
