Metadata-Version: 2.1
Name: jpndlpy
Version: 0.2.0
Summary: requests wrapper library for obtaining book information from the Japan National Diet Library.
Home-page: https://github.com/shimakaze-git/jpndlpy
Author: shimakaze-git
Author-email: shimakaze.soft@gmail.com
License: BSD 2-Clause 
Keywords: python requests
Platform: UNKNOWN
Classifier: Programming Language :: Python :: 3
Classifier: Programming Language :: Python :: 3.4
Classifier: Programming Language :: Python :: 3.6
Classifier: Programming Language :: Python :: 3.7
Classifier: License :: OSI Approved :: BSD License
Requires-Python: >=3.4, !=2.7.*
